perfsizesagemaker/__init__.py
perfsizesagemaker/constants.py
perfsizesagemaker/cost.py
perfsizesagemaker/credentials.py
perfsizesagemaker/environment/__init__.py
perfsizesagemaker/environment/sagemaker.py
perfsizesagemaker/load/__init__.py
perfsizesagemaker/load/sagemaker.py
perfsizesagemaker/main.py
perfsizesagemaker/py.typed
perfsizesagemaker/reporter/__init__.py
perfsizesagemaker/reporter/html.py
perfsizesagemaker/step/__init__.py
perfsizesagemaker/step/sagemaker.py
perfsizesagemaker-0.1.3.dist-info/LICENSE
perfsizesagemaker-0.1.3.dist-info/WHEEL
perfsizesagemaker-0.1.3.dist-info/METADATA
perfsizesagemaker-0.1.3.dist-info/RECORD
